{
  "id": "a87f04984f0a2d9b361da24ff21178b8",
  "sport_key": "soccer_spain_la_liga",
  "sport_title": "La Liga - Spain",
  "commence_time": "2026-01-17T17:30:00Z",
  "home_team": "CA Osasuna",
  "away_team": "Oviedo",
  "bookmakers": [
    {
      "key": "pinnacle",
      "title": "Pinnacle",
      "last_update": "2026-01-07T08:08:20Z",
      "markets": [
        {
          "key": "h2h",
          "last_update": "2026-01-07T08:08:20Z",
          "outcomes": [
            {
              "name": "CA Osasuna",
              "price": 1.72
            },
            {
              "name": "Oviedo",
              "price": 5.34
            },
            {
              "name": "Draw",
              "price": 3.48
            }
          ]
        },
        {
          "key": "totals",
          "last_update": "2026-01-07T08:08:20Z",
          "outcomes": [
            {
              "name": "Over",
              "price": 2.07,
              "point": 2.25
            },
            {
              "name": "Under",
              "price": 1.78,
              "point": 2.25
            }
          ]
        }
      ]
    }
  ]
}